stapi_pydantic/__init__.py
stapi_pydantic/conformance.py
stapi_pydantic/constants.py
stapi_pydantic/datetime_interval.py
stapi_pydantic/filter.py
stapi_pydantic/json_schema_model.py
stapi_pydantic/opportunity.py
stapi_pydantic/order.py
stapi_pydantic/product.py
stapi_pydantic/py.typed
stapi_pydantic/queryables.py
stapi_pydantic/root.py
stapi_pydantic/shared.py
stapi_pydantic-0.1.0.dist-info/METADATA
stapi_pydantic-0.1.0.dist-info/WHEEL
stapi_pydantic-0.1.0.dist-info/entry_points.txt
stapi_pydantic-0.1.0.dist-info/RECORD
