Metadata-Version: 2.4
Name: stapi-pydantic
Version: 0.1.0
Summary: Pydantic models for Satellite Tasking API (STAPI) Specification
Author-email: Phil Varner <philvarner@gmail.com>, Pete Gadomski <pete.gadomski@gmail.com>
Requires-Python: >=3.11
Requires-Dist: cql2>=0.3.6
Requires-Dist: geojson-pydantic>=1.2.0
Requires-Dist: pydantic>=2.12
